transparent/__init__.py
transparent/grad_cam.py
transparent/igos.py
transparent/lime.py
transparent/lrp.py
transparent/shap.py
transparent/transparent.py
transparent/classification/__init__.py
transparent/classification/tree.py
transparent/contrastive/contrastive_gradcam.py
transparent/contrastive/contrastive_lime.py
transparent/contrastive/contrastive_lrp.py
transparent/regression/__init__.py
transparent/regression/regression.py
transparent-0.1.2.dist-info/LICENSE
transparent-0.1.2.dist-info/METADATA
transparent-0.1.2.dist-info/WHEEL
transparent-0.1.2.dist-info/top_level.txt
transparent-0.1.2.dist-info/RECORD
